TagScriptEngine/__init__.py
TagScriptEngine/_warnings.py
TagScriptEngine/exceptions.py
TagScriptEngine/interpreter.py
TagScriptEngine/py.typed
TagScriptEngine/utils.py
TagScriptEngine/verb.py
TagScriptEngine/adapter/__init__.py
TagScriptEngine/adapter/discordadapters.py
TagScriptEngine/adapter/functionadapter.py
TagScriptEngine/adapter/intadapter.py
TagScriptEngine/adapter/objectadapter.py
TagScriptEngine/adapter/redbotadapters.py
TagScriptEngine/adapter/stringadapter.py
TagScriptEngine/block/__init__.py
TagScriptEngine/block/allowedmentions.py
TagScriptEngine/block/assign.py
TagScriptEngine/block/breakblock.py
TagScriptEngine/block/case.py
TagScriptEngine/block/command.py
TagScriptEngine/block/comment.py
TagScriptEngine/block/control.py
TagScriptEngine/block/cooldown.py
TagScriptEngine/block/count.py
TagScriptEngine/block/embedblock.py
TagScriptEngine/block/fiftyfifty.py
TagScriptEngine/block/helpers.py
TagScriptEngine/block/loosevariablegetter.py
TagScriptEngine/block/mathblock.py
TagScriptEngine/block/randomblock.py
TagScriptEngine/block/range.py
TagScriptEngine/block/redirect.py
TagScriptEngine/block/replaceblock.py
TagScriptEngine/block/require_blacklist.py
TagScriptEngine/block/shortcutredirect.py
TagScriptEngine/block/stopblock.py
TagScriptEngine/block/strf.py
TagScriptEngine/block/strictvariablegetter.py
TagScriptEngine/block/substr.py
TagScriptEngine/block/urlencodeblock.py
TagScriptEngine/interface/__init__.py
TagScriptEngine/interface/adapter.py
TagScriptEngine/interface/block.py
AdvancedTagScriptEngine-3.2.2.dist-info/LICENSE
AdvancedTagScriptEngine-3.2.2.dist-info/METADATA
AdvancedTagScriptEngine-3.2.2.dist-info/WHEEL
AdvancedTagScriptEngine-3.2.2.dist-info/top_level.txt
AdvancedTagScriptEngine-3.2.2.dist-info/RECORD
