Metadata-Version: 2.1
Name: AdvancedTagScriptEngine
Version: 3.2.2
Summary: An easy drop in user-provided Templating system.
Home-page: https://github.com/japandotorg/TagScriptEngine
Author: inthedark.org & PhenoM4n4n
Author-email: support@melonbot.io
License: Creative Commons Attribution 4.0 International License
Keywords: tagscript,string-templating,discord.py
Classifier: Development Status :: 5 - Production/Stable
Classifier: Intended Audience :: Developers
Classifier: License :: Freely Distributable
Classifier: Natural Language :: English
Classifier: Operating System :: OS Independent
Classifier: Programming Language :: Python :: 3.8
Classifier: Programming Language :: Python :: 3.9
Classifier: Programming Language :: Python :: 3.10
Classifier: Programming Language :: Python :: 3.11
Classifier: Topic :: Internet
Classifier: Topic :: Software Development :: Libraries
Classifier: Topic :: Software Development :: Libraries :: Python Modules
Classifier: Topic :: Utilities
Classifier: Typing :: Typed
Requires-Python: >=3.8
License-File: LICENSE
Requires-Dist: pyparsing
Requires-Dist: typing-extensions
Provides-Extra: all
Requires-Dist: orjson ; extra == 'all'
Requires-Dist: discord.py >=2.4.0 ; extra == 'all'
Provides-Extra: discord
Requires-Dist: discord.py >=2.4.0 ; extra == 'discord'
